{
  "documents": [
    {
      "fields": {
        "name": {
          "stringValue": "デコイ"
        },
        "memo": {
          "stringValue": "威力を計る的として用意された浮遊機械。攻撃を感知すると自らぶつかりにいく。"
        },
        "degreeOfThreat": {
          "integerValue": "1"
        },
        "tags": {
          "arrayValue": {
            "values": [
              {
                "mapValue": {
                  "fields": {
                    "name": {
                      "stringValue": "機械"
                    }
                  }
                }
              },
              {
                "mapValue": {
                  "fields": {
                    "name": {
                      "stringValue": "人形"
                    }
                  }
                }
              }
            ]
          }
        },
        "cards": {
          "arrayValue": {
            "values": [
              {
                "mapValue": {
                  "fields": {
                    "effect": {
                      "stringValue": "対象が受けたダメージを、代わりに自身が受ける。このカードは使用済にならない。"
                    },
                    "timing": {
                      "stringValue": "割込"
                    },
                    "target": {
                      "stringValue": "単体"
                    },
                    "cardName": {
                      "stringValue": "庇う"
                    },
                    "cost": {
                      "integerValue": "1"
                    },
                    "range": {
                      "integerValue": "0"
                    },
                    "maxRange": {
                      "integerValue": "1"
                    }
                  }
                }
              },
              {
                "mapValue": {
                  "fields": {
                    "cardName": {
                      "stringValue": "体当たり"
                    },
                    "effect": {
                      "stringValue": "ダメージ1"
                    },
                    "timing": {
                      "stringValue": "アクション"
                    },
                    "target": {
                      "stringValue": "単体"
                    },
                    "cost": {
                      "integerValue": "4"
                    },
                    "range": {
                      "integerValue": "0"
                    }
                  }
                }
              }
            ]
          }
        },
        "enemyId": {
          "stringValue": "kHvKakx3TqLFAeR9eSHZ"
        },
        "activePower": {
          "integerValue": "8"
        }
      }
    },
    {
      "fields": {
        "name": {
          "stringValue": "シールドデコイ"
        },
        "memo": {
          "stringValue": "軽い衝撃に耐えられるようにしたデコイ。"
        },
        "degreeOfThreat": {
          "integerValue": "1"
        },
        "tags": {
          "arrayValue": {
            "values": [
              {
                "mapValue": {
                  "fields": {
                    "name": {
                      "stringValue": "機械"
                    }
                  }
                }
              },
              {
                "mapValue": {
                  "fields": {
                    "name": {
                      "stringValue": "人形"
                    }
                  }
                }
              }
            ]
          }
        },
        "cards": {
          "arrayValue": {
            "values": [
              {
                "mapValue": {
                  "fields": {
                    "cardName": {
                      "stringValue": "庇う"
                    },
                    "effect": {
                      "stringValue": "対象が受けたダメージを、代わりに自身が受ける。このカードは使用済にならない。"
                    },
                    "timing": {
                      "stringValue": "割込"
                    },
                    "cost": {
                      "integerValue": "1"
                    },
                    "range": {
                      "integerValue": "0"
                    },
                    "maxRange": {
                      "integerValue": "1"
                    },
                    "target": {
                      "stringValue": "単体"
                    }
                  }
                }
              },
              {
                "mapValue": {
                  "fields": {
                    "cardName": {
                      "stringValue": "体当たり"
                    },
                    "effect": {
                      "stringValue": "ダメージ1"
                    },
                    "timing": {
                      "stringValue": "アクション"
                    },
                    "target": {
                      "stringValue": "単体"
                    },
                    "cost": {
                      "integerValue": "4"
                    },
                    "range": {
                      "integerValue": "0"
                    }
                  }
                }
              },
              {
                "mapValue": {
                  "fields": {
                    "cardName": {
                      "stringValue": "シールド"
                    },
                    "effect": {
                      "stringValue": "防御1"
                    },
                    "timing": {
                      "stringValue": "ダメージ"
                    },
                    "cost": {
                      "integerValue": "1"
                    },
                    "range": {
                      "integerValue": "0"
                    },
                    "target": {
                      "stringValue": "自身"
                    }
                  }
                }
              }
            ]
          }
        },
        "enemyId": {
          "stringValue": "kHvKakx3TqLFAeR9eSHZ"
        },
        "activePower": {
          "integerValue": "6"
        }
      }
    },
    {
      "fields": {
        "name": {
          "stringValue": "コマンダー"
        },
        "memo": {
          "stringValue": "浮遊機械制御用の個体"
        },
        "degreeOfThreat": {
          "integerValue": "2"
        },
        "tags": {
          "arrayValue": {
            "values": [
              {
                "mapValue": {
                  "fields": {
                    "name": {
                      "stringValue": "機械"
                    }
                  }
                }
              },
              {
                "mapValue": {
                  "fields": {
                    "name": {
                      "stringValue": "人形"
                    }
                  }
                }
              }
            ]
          }
        },
        "cards": {
          "arrayValue": {
            "values": [
              {
                "mapValue": {
                  "fields": {
                    "cardName": {
                      "stringValue": "行進指揮"
                    },
                    "effect": {
                      "stringValue": "移動0～1。対象は拒否可能。移動方向は対象ごとに決定。"
                    },
                    "timing": {
                      "stringValue": "アクション"
                    },
                    "target": {
                      "stringValue": "範囲"
                    },
                    "cost": {
                      "integerValue": "4"
                    },
                    "range": {
                      "integerValue": "0"
                    },
                    "maxRange": {
                      "integerValue": "1"
                    }
                  }
                }
              },
              {
                "mapValue": {
                  "fields": {
                    "cardName": {
                      "stringValue": "ビーム"
                    },
                    "effect": {
                      "stringValue": "ダメージ2"
                    },
                    "timing": {
                      "stringValue": "アクション"
                    },
                    "target": {
                      "stringValue": "単体"
                    },
                    "cost": {
                      "integerValue": "4"
                    },
                    "range": {
                      "integerValue": "1"
                    }
                  }
                }
              },
              {
                "mapValue": {
                  "fields": {
                    "cardName": {
                      "stringValue": "ふよふよ"
                    },
                    "effect": {
                      "stringValue": "移動1"
                    },
                    "timing": {
                      "stringValue": "アクション"
                    },
                    "target": {
                      "stringValue": "自身"
                    },
                    "cost": {
                      "integerValue": "4"
                    },
                    "range": {
                      "integerValue": "0"
                    }
                  }
                }
              }
            ]
          }
        },
        "enemyId": {
          "stringValue": "kHvKakx3TqLFAeR9eSHZ"
        },
        "activePower": {
          "integerValue": "8"
        }
      }
    },
    {
      "fields": {
        "name": {
          "stringValue": "ジャマー"
        },
        "memo": {
          "stringValue": "妨害音波を発生させる浮遊機械。"
        },
        "degreeOfThreat": {
          "integerValue": "1"
        },
        "tags": {
          "arrayValue": {
            "values": [
              {
                "mapValue": {
                  "fields": {
                    "name": {
                      "stringValue": "機械"
                    }
                  }
                }
              },
              {
                "mapValue": {
                  "fields": {
                    "name": {
                      "stringValue": "人形"
                    }
                  }
                }
              }
            ]
          }
        },
        "cards": {
          "arrayValue": {
            "values": [
              {
                "mapValue": {
                  "fields": {
                    "cardName": {
                      "stringValue": "ノイズ"
                    },
                    "effect": {
                      "stringValue": "妨害1"
                    },
                    "timing": {
                      "stringValue": "判定直後"
                    },
                    "target": {
                      "stringValue": "単体"
                    },
                    "cost": {
                      "integerValue": "0"
                    },
                    "range": {
                      "integerValue": "0"
                    }
                  }
                }
              },
              {
                "mapValue": {
                  "fields": {
                    "cardName": {
                      "stringValue": "体当たり"
                    },
                    "effect": {
                      "stringValue": "ダメージ1"
                    },
                    "timing": {
                      "stringValue": "アクション"
                    },
                    "target": {
                      "stringValue": "単体"
                    },
                    "cost": {
                      "integerValue": "4"
                    },
                    "range": {
                      "integerValue": "0"
                    }
                  }
                }
              }
            ]
          }
        },
        "enemyId": {
          "stringValue": "kHvKakx3TqLFAeR9eSHZ"
        },
        "activePower": {
          "integerValue": "8"
        }
      }
    }
  ]
}